flask_sqlalchemy_extended/__init__.py
flask_sqlalchemy_extended/model.py
sqlalchemy_extended/__init__.py
sqlalchemy_extended/orm/__init__.py
sqlalchemy_extended/orm/scoping.py
flask_sqlalchemy_extended-0.0.22.dist-info/LICENSE
flask_sqlalchemy_extended-0.0.22.dist-info/METADATA
flask_sqlalchemy_extended-0.0.22.dist-info/WHEEL
flask_sqlalchemy_extended-0.0.22.dist-info/top_level.txt
flask_sqlalchemy_extended-0.0.22.dist-info/RECORD
