Metadata-Version: 2.1
Name: flask-sqlalchemy-extended
Version: 0.0.22
Summary: SQLAlchemy autocomplete
Home-page: https://github.com/luanws/flask-sqlalchemy-extended
Author: luanws
Author-email: luan.w.silveira@gmail.com
License: UNKNOWN
Platform: UNKNOWN
Classifier: Programming Language :: Python :: 3
Classifier: License :: OSI Approved :: MIT License
Classifier: Operating System :: OS Independent
Requires-Python: >=3.6
